README.md
setup.py
.greplog/default.py
.greplog/servers.py
greplog/__init__.py
greplog/api.py
greplog/bin.py
greplog/config.py
greplog/remote.py
greplog.egg-info/PKG-INFO
greplog.egg-info/SOURCES.txt
greplog.egg-info/dependency_links.txt
greplog.egg-info/entry_points.txt
greplog.egg-info/requires.txt
greplog.egg-info/top_level.txt